{
	"pattrstorage" : 	{
		"name" : "hue_shift",
		"slots" : 		{
			"1" : 			{
				"id" : 1,
				"data" : 				{
					"audio_divisor" : [ 1000.0 ],
					"live.gain~" : [  ],
					"live.tab" : [ 0.0 ],
					"slide_down" : [ 10.0 ],
					"slide_up" : [ 10.0 ],
					"effect-mult" : [ 5.0 ],
					"sc.texture.rgb2hsl::bypass" : [ 0.0 ],
					"sc.texture.hsl2rgb::bypass" : [ 0.0 ],
					"Video Input Settings::sc.texture.xfade::xfade" : [ 0.0 ],
					"Video Input Settings::sc.texture.xfade::bypass" : [ 0.0 ],
					"Video Input Settings::sc.texture.camera.simple::hflip" : [ 1.0 ],
					"Video Input Settings::sc.texture.camera.simple::automatic[1]" : [ 1 ],
					"Video Input Settings::sc.texture.camera.simple::unique" : [ 1 ],
					"Video Input Settings::sc.texture.camera.simple::texture_name" : [ 0 ],
					"Video Input Settings::sc.texture.syphon.input::appname" : [ "" ],
					"Video Input Settings::sc.texture.syphon.input::servername" : [ "" ],
					"Video Input Settings::sc.texture.syphon.input::drawto" : [ "a_hue_shift" ],
					"Video Input Settings::sc.texture.xfade[1]::bypass" : [ 0.0 ],
					"Video Input Settings::sc.texture.xfade[1]::xfade" : [ 0.5 ]
				}

			}
,
			"2" : 			{
				"id" : 2,
				"data" : 				{
					"audio_divisor" : [ 10000.0 ],
					"live.gain~" : [  ],
					"live.tab" : [ 0.0 ],
					"slide_down" : [ 100.0 ],
					"slide_up" : [ 100.0 ],
					"effect-mult" : [ 5.0 ],
					"sc.texture.rgb2hsl::bypass" : [ 0.0 ],
					"sc.texture.hsl2rgb::bypass" : [ 0.0 ],
					"Video Input Settings::sc.texture.xfade::xfade" : [ 0.0 ],
					"Video Input Settings::sc.texture.xfade::bypass" : [ 0.0 ],
					"Video Input Settings::sc.texture.camera.simple::hflip" : [ 1.0 ],
					"Video Input Settings::sc.texture.camera.simple::automatic[1]" : [ 1 ],
					"Video Input Settings::sc.texture.camera.simple::unique" : [ 1 ],
					"Video Input Settings::sc.texture.camera.simple::texture_name" : [ 0 ],
					"Video Input Settings::sc.texture.syphon.input::appname" : [ "" ],
					"Video Input Settings::sc.texture.syphon.input::servername" : [ "" ],
					"Video Input Settings::sc.texture.syphon.input::drawto" : [ "a_hue_shift" ],
					"Video Input Settings::sc.texture.xfade[1]::bypass" : [ 0.0 ],
					"Video Input Settings::sc.texture.xfade[1]::xfade" : [ 0.5 ]
				}

			}
,
			"3" : 			{
				"id" : 3,
				"data" : 				{
					"audio_divisor" : [ 1000.0 ],
					"live.gain~" : [  ],
					"live.tab" : [ 0.0 ],
					"slide_down" : [ 50.0 ],
					"slide_up" : [ 50.0 ],
					"effect-mult" : [ 5.0 ],
					"sc.texture.rgb2hsl::bypass" : [ 0.0 ],
					"sc.texture.hsl2rgb::bypass" : [ 0.0 ],
					"Video Input Settings::sc.texture.xfade::xfade" : [ 0.0 ],
					"Video Input Settings::sc.texture.xfade::bypass" : [ 0.0 ],
					"Video Input Settings::sc.texture.camera.simple::hflip" : [ 1.0 ],
					"Video Input Settings::sc.texture.camera.simple::automatic[1]" : [ 1 ],
					"Video Input Settings::sc.texture.camera.simple::unique" : [ 1 ],
					"Video Input Settings::sc.texture.camera.simple::texture_name" : [ 0 ],
					"Video Input Settings::sc.texture.syphon.input::appname" : [ "" ],
					"Video Input Settings::sc.texture.syphon.input::servername" : [ "" ],
					"Video Input Settings::sc.texture.syphon.input::drawto" : [ "a_hue_shift" ],
					"Video Input Settings::sc.texture.xfade[1]::bypass" : [ 0.0 ],
					"Video Input Settings::sc.texture.xfade[1]::xfade" : [ 0.5 ]
				}

			}
,
			"4" : 			{
				"id" : 4,
				"data" : 				{
					"audio_divisor" : [ 1000.0 ],
					"live.gain~" : [  ],
					"live.tab" : [ 1.0 ],
					"slide_down" : [ 10.0 ],
					"slide_up" : [ 10.0 ],
					"effect-mult" : [ 5.0 ],
					"sc.texture.rgb2hsl::bypass" : [ 0.0 ],
					"sc.texture.hsl2rgb::bypass" : [ 0.0 ],
					"Video Input Settings::sc.texture.xfade::xfade" : [ 0.0 ],
					"Video Input Settings::sc.texture.xfade::bypass" : [ 0.0 ],
					"Video Input Settings::sc.texture.camera.simple::hflip" : [ 1.0 ],
					"Video Input Settings::sc.texture.camera.simple::automatic[1]" : [ 1 ],
					"Video Input Settings::sc.texture.camera.simple::unique" : [ 1 ],
					"Video Input Settings::sc.texture.camera.simple::texture_name" : [ 0 ],
					"Video Input Settings::sc.texture.syphon.input::appname" : [ "" ],
					"Video Input Settings::sc.texture.syphon.input::servername" : [ "" ],
					"Video Input Settings::sc.texture.syphon.input::drawto" : [ "a_hue_shift" ],
					"Video Input Settings::sc.texture.xfade[1]::bypass" : [ 0.0 ],
					"Video Input Settings::sc.texture.xfade[1]::xfade" : [ 0.5 ]
				}

			}
,
			"5" : 			{
				"id" : 5,
				"data" : 				{
					"audio_divisor" : [ 1000.0 ],
					"live.gain~" : [  ],
					"live.tab" : [ 1.0 ],
					"slide_down" : [ 50.0 ],
					"slide_up" : [ 50.0 ],
					"effect-mult" : [ 5.0 ],
					"sc.texture.rgb2hsl::bypass" : [ 0.0 ],
					"sc.texture.hsl2rgb::bypass" : [ 0.0 ],
					"Video Input Settings::sc.texture.xfade::xfade" : [ 0.0 ],
					"Video Input Settings::sc.texture.xfade::bypass" : [ 0.0 ],
					"Video Input Settings::sc.texture.camera.simple::hflip" : [ 1.0 ],
					"Video Input Settings::sc.texture.camera.simple::automatic[1]" : [ 1 ],
					"Video Input Settings::sc.texture.camera.simple::unique" : [ 1 ],
					"Video Input Settings::sc.texture.camera.simple::texture_name" : [ 0 ],
					"Video Input Settings::sc.texture.syphon.input::appname" : [ "" ],
					"Video Input Settings::sc.texture.syphon.input::servername" : [ "" ],
					"Video Input Settings::sc.texture.syphon.input::drawto" : [ "a_hue_shift" ],
					"Video Input Settings::sc.texture.xfade[1]::bypass" : [ 0.0 ],
					"Video Input Settings::sc.texture.xfade[1]::xfade" : [ 0.5 ]
				}

			}
,
			"6" : 			{
				"id" : 6,
				"data" : 				{
					"audio_divisor" : [ 1000.0 ],
					"live.gain~" : [  ],
					"live.tab" : [ 1.0 ],
					"slide_down" : [ 50.0 ],
					"slide_up" : [ 50.0 ],
					"effect-mult" : [ 5.0 ],
					"sc.texture.rgb2hsl::bypass" : [ 0.0 ],
					"sc.texture.hsl2rgb::bypass" : [ 0.0 ],
					"Video Input Settings::sc.texture.xfade::xfade" : [ 0.0 ],
					"Video Input Settings::sc.texture.xfade::bypass" : [ 0.0 ],
					"Video Input Settings::sc.texture.camera.simple::hflip" : [ 1.0 ],
					"Video Input Settings::sc.texture.camera.simple::automatic[1]" : [ 1 ],
					"Video Input Settings::sc.texture.camera.simple::unique" : [ 1 ],
					"Video Input Settings::sc.texture.camera.simple::texture_name" : [ 0 ],
					"Video Input Settings::sc.texture.syphon.input::appname" : [ "" ],
					"Video Input Settings::sc.texture.syphon.input::servername" : [ "" ],
					"Video Input Settings::sc.texture.syphon.input::drawto" : [ "a_hue_shift" ],
					"Video Input Settings::sc.texture.xfade[1]::bypass" : [ 0.0 ],
					"Video Input Settings::sc.texture.xfade[1]::xfade" : [ 0.5 ]
				}

			}
,
			"7" : 			{
				"id" : 7,
				"data" : 				{
					"audio_divisor" : [ 1000.0 ],
					"live.gain~" : [  ],
					"live.tab" : [ 2.0 ],
					"slide_down" : [ 10.0 ],
					"slide_up" : [ 10.0 ],
					"effect-mult" : [ 5.0 ],
					"sc.texture.rgb2hsl::bypass" : [ 0.0 ],
					"sc.texture.hsl2rgb::bypass" : [ 0.0 ],
					"Video Input Settings::sc.texture.xfade::xfade" : [ 0.0 ],
					"Video Input Settings::sc.texture.xfade::bypass" : [ 0.0 ],
					"Video Input Settings::sc.texture.camera.simple::hflip" : [ 1.0 ],
					"Video Input Settings::sc.texture.camera.simple::automatic[1]" : [ 1 ],
					"Video Input Settings::sc.texture.camera.simple::unique" : [ 1 ],
					"Video Input Settings::sc.texture.camera.simple::texture_name" : [ 0 ],
					"Video Input Settings::sc.texture.syphon.input::appname" : [ "" ],
					"Video Input Settings::sc.texture.syphon.input::servername" : [ "" ],
					"Video Input Settings::sc.texture.syphon.input::drawto" : [ "a_hue_shift" ],
					"Video Input Settings::sc.texture.xfade[1]::bypass" : [ 0.0 ],
					"Video Input Settings::sc.texture.xfade[1]::xfade" : [ 0.5 ]
				}

			}
,
			"8" : 			{
				"id" : 8,
				"data" : 				{
					"audio_divisor" : [ 10000.0 ],
					"live.gain~" : [  ],
					"live.tab" : [ 2.0 ],
					"slide_down" : [ 100.0 ],
					"slide_up" : [ 100.0 ],
					"effect-mult" : [ 5.0 ],
					"sc.texture.rgb2hsl::bypass" : [ 0.0 ],
					"sc.texture.hsl2rgb::bypass" : [ 0.0 ],
					"Video Input Settings::sc.texture.xfade::xfade" : [ 0.0 ],
					"Video Input Settings::sc.texture.xfade::bypass" : [ 0.0 ],
					"Video Input Settings::sc.texture.camera.simple::hflip" : [ 1.0 ],
					"Video Input Settings::sc.texture.camera.simple::automatic[1]" : [ 1 ],
					"Video Input Settings::sc.texture.camera.simple::unique" : [ 1 ],
					"Video Input Settings::sc.texture.camera.simple::texture_name" : [ 0 ],
					"Video Input Settings::sc.texture.syphon.input::appname" : [ "" ],
					"Video Input Settings::sc.texture.syphon.input::servername" : [ "" ],
					"Video Input Settings::sc.texture.syphon.input::drawto" : [ "a_hue_shift" ],
					"Video Input Settings::sc.texture.xfade[1]::bypass" : [ 0.0 ],
					"Video Input Settings::sc.texture.xfade[1]::xfade" : [ 0.5 ]
				}

			}
,
			"9" : 			{
				"id" : 9,
				"data" : 				{
					"audio_divisor" : [ 1000.0 ],
					"live.gain~" : [  ],
					"live.tab" : [ 2.0 ],
					"slide_down" : [ 50.0 ],
					"slide_up" : [ 50.0 ],
					"effect-mult" : [ 5.0 ],
					"sc.texture.rgb2hsl::bypass" : [ 0.0 ],
					"sc.texture.hsl2rgb::bypass" : [ 0.0 ],
					"Video Input Settings::sc.texture.xfade::xfade" : [ 0.0 ],
					"Video Input Settings::sc.texture.xfade::bypass" : [ 0.0 ],
					"Video Input Settings::sc.texture.camera.simple::hflip" : [ 1.0 ],
					"Video Input Settings::sc.texture.camera.simple::automatic[1]" : [ 1 ],
					"Video Input Settings::sc.texture.camera.simple::unique" : [ 1 ],
					"Video Input Settings::sc.texture.camera.simple::texture_name" : [ 0 ],
					"Video Input Settings::sc.texture.syphon.input::appname" : [ "" ],
					"Video Input Settings::sc.texture.syphon.input::servername" : [ "" ],
					"Video Input Settings::sc.texture.syphon.input::drawto" : [ "a_hue_shift" ],
					"Video Input Settings::sc.texture.xfade[1]::bypass" : [ 0.0 ],
					"Video Input Settings::sc.texture.xfade[1]::xfade" : [ 0.5 ]
				}

			}

		}

	}

}
